{"title":"Candy Shop - Holy Its Huge","uid":8988512,"size":1459206144,"categoryP":"porn","categoryS":"movies","magnet":"?xt=urn:btih:01cf854222cc5167d84cbd4f6fdf519c45f81846&amp;dn=Candy+Shop+-+Holy+Its+Huge&amp;tr=udp%3A%2F%2Ftracker.openbittorrent.com%3A80&amp;tr=udp%3A%2F%2Fopen.demonii.com%3A1337&amp;tr=udp%3A%2F%2Ftracker.coppersurfer.tk%3A6969&amp;tr=udp%3A%2F%2Fexodus.desync.com%3A6969","seeders":0,"leechers":1,"uploader":"irealu69","files":-1,"time":1380735079,"description":"Candy Shop - Holy Its Huge\n~~~~~~~~~~~~~~~~~~~~~~~~~~\n\nScreenshots:\n~~~~~~~~~~~\n &lt;a href=&quot;\nhttp://picturevip.com/x/clean/47z&quot; rel=&quot;nofollow&quot; target=&quot;_NEW&quot;&gt;\nhttp://picturevip.com/x/clean/47z&lt;/a&gt;\n &lt;a href=&quot;\nhttp://picturevip.com/x/clean/47S&quot; rel=&quot;nofollow&quot; target=&quot;_NEW&quot;&gt;\nhttp://picturevip.com/x/clean/47S&lt;/a&gt;\n &lt;a href=&quot;\nhttp://picturevip.com/x/clean/475&quot; rel=&quot;nofollow&quot; target=&quot;_NEW&quot;&gt;\nhttp://picturevip.com/x/clean/475&lt;/a&gt;\n &lt;a href=&quot;\nhttp://picturevip.com/x/clean/47B&quot; rel=&quot;nofollow&quot; target=&quot;_NEW&quot;&gt;\nhttp://picturevip.com/x/clean/47B&lt;/a&gt;\n &lt;a href=&quot;\nhttp://picturevip.com/x/clean/47K&quot; rel=&quot;nofollow&quot; target=&quot;_NEW&quot;&gt;\nhttp://picturevip.com/x/clean/47K&lt;/a&gt;\n\n\nVideos Info:\n~~~~~~~~~~~~\nSize: 1.359 GB\nResolution: 512x384","torrent":{"xt":"urn:btih:01cf854222cc5167d84cbd4f6fdf519c45f81846","amp;dn":"Candy+Shop+-+Holy+Its+Huge","amp;tr":["udp%3A%2F%2Ftracker.openbittorrent.com%3A80","udp%3A%2F%2Fopen.demonii.com%3A1337","udp%3A%2F%2Ftracker.coppersurfer.tk%3A6969","udp%3A%2F%2Fexodus.desync.com%3A6969"],"infoHash":"01cf854222cc5167d84cbd4f6fdf519c45f81846","infoHashBuffer":{"type":"Buffer","data":[1,207,133,66,34,204,81,103,216,76,189,79,111,223,81,156,69,248,24,70]},"announce":[],"urlList":[]}}