{"title":"Home.And.Away.Weekly.2013.09.23","uid":8979804,"size":1740870132,"categoryP":"video","categoryS":"tv_shows","magnet":"?xt=urn:btih:04dc1eb613f32ac8f8ed57db1ecd1b92fb15009e&amp;dn=Home.And.Away.Weekly.2013.09.23&amp;tr=udp%3A%2F%2Ftracker.openbittorrent.com%3A80&amp;tr=udp%3A%2F%2Fopen.demonii.com%3A1337&amp;tr=udp%3A%2F%2Ftracker.coppersurfer.tk%3A6969&amp;tr=udp%3A%2F%2Fexodus.desync.com%3A6969","seeders":0,"leechers":1,"uploader":"mickedee77","files":4,"time":1380533124,"description":"Home &amp; Away\nMonday 23rd September 2013\nTuesday 24th September 2013\nWednesday 25th September 2013\nThursday 26th September 2013 (Double Episode)","torrent":{"xt":"urn:btih:04dc1eb613f32ac8f8ed57db1ecd1b92fb15009e","amp;dn":"Home.And.Away.Weekly.2013.09.23","amp;tr":["udp%3A%2F%2Ftracker.openbittorrent.com%3A80","udp%3A%2F%2Fopen.demonii.com%3A1337","udp%3A%2F%2Ftracker.coppersurfer.tk%3A6969","udp%3A%2F%2Fexodus.desync.com%3A6969"],"infoHash":"04dc1eb613f32ac8f8ed57db1ecd1b92fb15009e","infoHashBuffer":{"type":"Buffer","data":[4,220,30,182,19,243,42,200,248,237,87,219,30,205,27,146,251,21,0,158]},"announce":[],"urlList":[]}}