{"title":"Objets Caches PJ-Pack Dvd vol.22 (VF)","uid":9024011,"size":4629056488,"categoryP":"games","categoryS":"pc","magnet":"?xt=urn:btih:0e2db185c17190b640c5de6121b1502b0d0cd70d&amp;dn=Objets+Caches+PJ-Pack+Dvd+vol.22+%28VF%29&amp;tr=udp%3A%2F%2Ftracker.openbittorrent.com%3A80&amp;tr=udp%3A%2F%2Fopen.demonii.com%3A1337&amp;tr=udp%3A%2F%2Ftracker.coppersurfer.tk%3A6969&amp;tr=udp%3A%2F%2Fexodus.desync.com%3A6969","seeders":0,"leechers":0,"uploader":"Hybou","files":10,"time":1381330589,"description":"Jeux en francais","torrent":{"xt":"urn:btih:0e2db185c17190b640c5de6121b1502b0d0cd70d","amp;dn":"Objets+Caches+PJ-Pack+Dvd+vol.22+%28VF%29","amp;tr":["udp%3A%2F%2Ftracker.openbittorrent.com%3A80","udp%3A%2F%2Fopen.demonii.com%3A1337","udp%3A%2F%2Ftracker.coppersurfer.tk%3A6969","udp%3A%2F%2Fexodus.desync.com%3A6969"],"infoHash":"0e2db185c17190b640c5de6121b1502b0d0cd70d","infoHashBuffer":{"type":"Buffer","data":[14,45,177,133,193,113,144,182,64,197,222,97,33,177,80,43,13,12,215,13]},"announce":[],"urlList":[]}}