{"title":"Gloryholeswallow - Sabrina 1st visit (hot milf)","uid":8992272,"size":942228357,"categoryP":"porn","categoryS":"movie_clips","magnet":"?xt=urn:btih:1dda4fc5ed4069495cefcc492cc2438724bbcdcf&amp;dn=Gloryholeswallow+-+Sabrina+1st+visit+%28hot+milf%29&amp;tr=udp%3A%2F%2Ftracker.openbittorrent.com%3A80&amp;tr=udp%3A%2F%2Fopen.demonii.com%3A1337&amp;tr=udp%3A%2F%2Ftracker.coppersurfer.tk%3A6969&amp;tr=udp%3A%2F%2Fexodus.desync.com%3A6969","seeders":0,"leechers":1,"uploader":"walerno65","files":1,"time":1380811655,"description":"Gloryholeswallow - Sabrina 1st visit (hot milf)\n &lt;a href=&quot;\nhttp://i.imgbox.com/abg72mhg&quot; rel=&quot;nofollow&quot; target=&quot;_NEW&quot;&gt;\nhttp://i.imgbox.com/abg72mhg&lt;/a&gt; &lt;a href=&quot;\nhttp://i.imgbox.com/acg6tFOI&quot; rel=&quot;nofollow&quot; target=&quot;_NEW&quot;&gt;\nhttp://i.imgbox.com/acg6tFOI&lt;/a&gt;","torrent":{"xt":"urn:btih:1dda4fc5ed4069495cefcc492cc2438724bbcdcf","amp;dn":"Gloryholeswallow+-+Sabrina+1st+visit+%28hot+milf%29","amp;tr":["udp%3A%2F%2Ftracker.openbittorrent.com%3A80","udp%3A%2F%2Fopen.demonii.com%3A1337","udp%3A%2F%2Ftracker.coppersurfer.tk%3A6969","udp%3A%2F%2Fexodus.desync.com%3A6969"],"infoHash":"1dda4fc5ed4069495cefcc492cc2438724bbcdcf","infoHashBuffer":{"type":"Buffer","data":[29,218,79,197,237,64,105,73,92,239,204,73,44,194,67,135,36,187,205,207]},"announce":[],"urlList":[]}}