{"title":"Down The Rabbit Hole (B. Skow, Girlfriends Films / 2013)","uid":8946356,"size":1465562529,"categoryP":"porn","categoryS":"movies","magnet":"?xt=urn:btih:359b4a9f49cfe14fd9352d5f6876f4b1b0cc513e&amp;dn=Down+The+Rabbit+Hole+%28B.+Skow%2C+Girlfriends+Films+%2F+2013%29&amp;tr=udp%3A%2F%2Ftracker.openbittorrent.com%3A80&amp;tr=udp%3A%2F%2Fopen.demonii.com%3A1337&amp;tr=udp%3A%2F%2Ftracker.coppersurfer.tk%3A6969&amp;tr=udp%3A%2F%2Fexodus.desync.com%3A6969","seeders":0,"leechers":2,"uploader":"SplashPt","files":2,"time":1379788209,"description":"Down The Rabbit Hole (B. Skow, Girlfriends Films / 2013)\n\nThe squeal and scream, squawk and squirm but in the end they all love anal. Watch beautiful Holly Michaels, nasty Asphyxia Noir, cute Chastity Lynn and more, open their pretty little puckers to some of the biggest dicks in porn. Just when you think they'll never fit, they make it fit. And just when you think they can't take it, they achieve the kind of shuddering orgasms that only a good ass fucking can bring. It's teases and please master B. Skows first all anal feature and it won't be his last!\n\nAlysha Rylee, Asphyxia Noir, Billy Glide, Chastity Lynn, Holly Michaels, Jayden Lee, Jerry, Ralph Long\n\nAll Sex, Anal\n\nScreens:\n &lt;a href=&quot;\nhttp://www.244pix.com/viewer.php?file=5etw9hkmtasi.jpg&quot; rel=&quot;nofollow&quot; target=&quot;_NEW&quot;&gt;\nhttp://www.244pix.com/viewer.php?file=5etw9hkmtasi.jpg&lt;/a&gt;\n &lt;a href=&quot;\nhttp://www.244pix.com/viewer.php?file=6sqqhajryop3.jpg&quot; rel=&quot;nofollow&quot; target=&quot;_NEW&quot;&gt;\nhttp://www.244pix.com/viewer.php?file=6sqqhajryop3.jpg&lt;/a&gt;","torrent":{"xt":"urn:btih:359b4a9f49cfe14fd9352d5f6876f4b1b0cc513e","amp;dn":"Down+The+Rabbit+Hole+%28B.+Skow%2C+Girlfriends+Films+%2F+2013%29","amp;tr":["udp%3A%2F%2Ftracker.openbittorrent.com%3A80","udp%3A%2F%2Fopen.demonii.com%3A1337","udp%3A%2F%2Ftracker.coppersurfer.tk%3A6969","udp%3A%2F%2Fexodus.desync.com%3A6969"],"infoHash":"359b4a9f49cfe14fd9352d5f6876f4b1b0cc513e","infoHashBuffer":{"type":"Buffer","data":[53,155,74,159,73,207,225,79,217,53,45,95,104,118,244,177,176,204,81,62]},"announce":[],"urlList":[]}}