{"title":"Diesel - Let It Fly (2013) NLToppers","uid":8831309,"size":106242489,"categoryP":"audio","categoryS":"other","magnet":"?xt=urn:btih:3d721c2b414501aee4854fac40037422922d2702&amp;dn=Diesel+-+Let+It+Fly+%282013%29+NLToppers&amp;tr=udp%3A%2F%2Ftracker.openbittorrent.com%3A80&amp;tr=udp%3A%2F%2Fopen.demonii.com%3A1337&amp;tr=udp%3A%2F%2Ftracker.coppersurfer.tk%3A6969&amp;tr=udp%3A%2F%2Fexodus.desync.com%3A6969","seeders":0,"leechers":1,"uploader":"ore-sabre","files":-1,"time":1376989303,"description":"\n\n\nDiesel - Let It Fly (2013) NLToppers\n\n\n\nTracklist:\n\n\n01. Moneymaker (2:58)\n02. By Your Throne (3:13)\n03. One Phone Call (3:46)\n04. Cupid's Embrace (2:57)\n05. Last Shower (Feat. Tim Chaisson) (3:40)\n06. Let It Fly (4:29)\n07. Sound Of Guitar (4:21)\n08. If You Let Me Give (Feat. Lila Gold) (3:01)\n09. No Time Tonight (3:19)\n10. Navigate (4:03)\n11. Can't Feel You (3:01)\n12. The Miles (4:11)\n\nPostinfo:\n\nCategory : Sound\nBitrate  : 320kbps\nFormat   : MP3\nGenre    : Blues/Rock\n\n    Ore-sabre","torrent":{"xt":"urn:btih:3d721c2b414501aee4854fac40037422922d2702","amp;dn":"Diesel+-+Let+It+Fly+%282013%29+NLToppers","amp;tr":["udp%3A%2F%2Ftracker.openbittorrent.com%3A80","udp%3A%2F%2Fopen.demonii.com%3A1337","udp%3A%2F%2Ftracker.coppersurfer.tk%3A6969","udp%3A%2F%2Fexodus.desync.com%3A6969"],"infoHash":"3d721c2b414501aee4854fac40037422922d2702","infoHashBuffer":{"type":"Buffer","data":[61,114,28,43,65,69,1,174,228,133,79,172,64,3,116,34,146,45,39,2]},"announce":[],"urlList":[]}}