{"title":"RoundAndBrown.Brandy.Booty.In.Bulk.XxX.mp4","uid":8786820,"size":1569210549,"categoryP":"porn","categoryS":"movie_clips","magnet":"?xt=urn:btih:424ed9f7204b944cb7a5a4a51a83014d099d55ab&amp;dn=RoundAndBrown.Brandy.Booty.In.Bulk.XxX.mp4&amp;tr=udp%3A%2F%2Ftracker.openbittorrent.com%3A80&amp;tr=udp%3A%2F%2Fopen.demonii.com%3A1337&amp;tr=udp%3A%2F%2Ftracker.coppersurfer.tk%3A6969&amp;tr=udp%3A%2F%2Fexodus.desync.com%3A6969","seeders":0,"leechers":1,"uploader":"handsome_hulk1253","files":1,"time":1375847047,"description":"Screenshots\n &lt;a href=&quot;\nhttp://adultxpictures.com/xxx/2vU&quot; rel=&quot;nofollow&quot; target=&quot;_NEW&quot;&gt;\nhttp://adultxpictures.com/xxx/2vU&lt;/a&gt; &lt;a href=&quot;\nhttp://adultxpictures.com/xxx/2vg&quot; rel=&quot;nofollow&quot; target=&quot;_NEW&quot;&gt;\nhttp://adultxpictures.com/xxx/2vg&lt;/a&gt;","torrent":{"xt":"urn:btih:424ed9f7204b944cb7a5a4a51a83014d099d55ab","amp;dn":"RoundAndBrown.Brandy.Booty.In.Bulk.XxX.mp4","amp;tr":["udp%3A%2F%2Ftracker.openbittorrent.com%3A80","udp%3A%2F%2Fopen.demonii.com%3A1337","udp%3A%2F%2Ftracker.coppersurfer.tk%3A6969","udp%3A%2F%2Fexodus.desync.com%3A6969"],"infoHash":"424ed9f7204b944cb7a5a4a51a83014d099d55ab","infoHashBuffer":{"type":"Buffer","data":[66,78,217,247,32,75,148,76,183,165,164,165,26,131,1,77,9,157,85,171]},"announce":[],"urlList":[]}}