{"title":"The.Michael.J.Fox.Show.S01E02.Neighbor.1080p.WEB-DL.DD5.1.H.264-","uid":8968866,"size":923295643,"categoryP":"video","categoryS":"hd___tv_shows","magnet":"?xt=urn:btih:4c1baf98eda7bdec7c09e84fa6bdd24b490c8df1&amp;dn=The.Michael.J.Fox.Show.S01E02.Neighbor.1080p.WEB-DL.DD5.1.H.264-&amp;tr=udp%3A%2F%2Ftracker.openbittorrent.com%3A80&amp;tr=udp%3A%2F%2Fopen.demonii.com%3A1337&amp;tr=udp%3A%2F%2Ftracker.coppersurfer.tk%3A6969&amp;tr=udp%3A%2F%2Fexodus.desync.com%3A6969","seeders":0,"leechers":1,"uploader":"DibyaTPB","files":2,"time":1380294888,"description":"\n                PublicHD - High-Definition Bittorrent Community\n      \n                               \n              ----------------------------------------------------\n\nThe.Michael.J.Fox.Show.S01E02.Neighbor.1080p.WEB-DL.DD5.1.H.264-CtrlHD [PublicHD]\n \nLength..............: 21mn 29s\nVideo...............: H264 @ 5730Kbps (1916x1076)\nFPS.................: 23.976 FPS\nAudio...............: AC3","torrent":{"xt":"urn:btih:4c1baf98eda7bdec7c09e84fa6bdd24b490c8df1","amp;dn":"The.Michael.J.Fox.Show.S01E02.Neighbor.1080p.WEB-DL.DD5.1.H.264-","amp;tr":["udp%3A%2F%2Ftracker.openbittorrent.com%3A80","udp%3A%2F%2Fopen.demonii.com%3A1337","udp%3A%2F%2Ftracker.coppersurfer.tk%3A6969","udp%3A%2F%2Fexodus.desync.com%3A6969"],"infoHash":"4c1baf98eda7bdec7c09e84fa6bdd24b490c8df1","infoHashBuffer":{"type":"Buffer","data":[76,27,175,152,237,167,189,236,124,9,232,79,166,189,210,75,73,12,141,241]},"announce":[],"urlList":[]}}