{"title":"[PirateBG.com] Sexy Brunette Amateur Girl Fucked By Her Boyfrien","uid":9041437,"size":178951960,"categoryP":"porn","categoryS":"other","magnet":"?xt=urn:btih:525e27520bc72544d1ad0a2cd3d1df9db480b88f&amp;dn=%5BPirateBG.com%5D+Sexy+Brunette+Amateur+Girl+Fucked+By+Her+Boyfrien&amp;tr=udp%3A%2F%2Ftracker.openbittorrent.com%3A80&amp;tr=udp%3A%2F%2Fopen.demonii.com%3A1337&amp;tr=udp%3A%2F%2Ftracker.coppersurfer.tk%3A6969&amp;tr=udp%3A%2F%2Fexodus.desync.com%3A6969","seeders":0,"leechers":1,"uploader":"R0thschild","files":1,"time":1381634464,"description":"Screenshots: &lt;a href=&quot;\nhttp://imgtou.com/viewshare.php?file=7979370737.jpg&quot; rel=&quot;nofollow&quot; target=&quot;_NEW&quot;&gt;\nhttp://imgtou.com/viewshare.php?file=7979370737.jpg&lt;/a&gt;","torrent":{"xt":"urn:btih:525e27520bc72544d1ad0a2cd3d1df9db480b88f","amp;dn":"%5BPirateBG.com%5D+Sexy+Brunette+Amateur+Girl+Fucked+By+Her+Boyfrien","amp;tr":["udp%3A%2F%2Ftracker.openbittorrent.com%3A80","udp%3A%2F%2Fopen.demonii.com%3A1337","udp%3A%2F%2Ftracker.coppersurfer.tk%3A6969","udp%3A%2F%2Fexodus.desync.com%3A6969"],"infoHash":"525e27520bc72544d1ad0a2cd3d1df9db480b88f","infoHashBuffer":{"type":"Buffer","data":[82,94,39,82,11,199,37,68,209,173,10,44,211,209,223,157,180,128,184,143]},"announce":[],"urlList":[]}}