{"title":"RealWifeStories - Dani Daniels (08.05.2013.)","uid":8781185,"size":292235151,"categoryP":"porn","categoryS":"movie_clips","magnet":"?xt=urn:btih:5406625499d786f80ea5d3347a18bc4e6bed2540&amp;dn=RealWifeStories+-+Dani+Daniels+%2808.05.2013.%29&amp;tr=udp%3A%2F%2Ftracker.openbittorrent.com%3A80&amp;tr=udp%3A%2F%2Fopen.demonii.com%3A1337&amp;tr=udp%3A%2F%2Ftracker.coppersurfer.tk%3A6969&amp;tr=udp%3A%2F%2Fexodus.desync.com%3A6969","seeders":0,"leechers":0,"uploader":"kuzili1","files":-1,"time":1375715545,"description":"SCREENS :\n &lt;a href=&quot;\nhttp://www.pixsor.com/share-AAF6_51FFA496.html&quot; rel=&quot;nofollow&quot; target=&quot;_NEW&quot;&gt;\nhttp://www.pixsor.com/share-AAF6_51FFA496.html&lt;/a&gt;\n &lt;a href=&quot;\nhttp://www.pixsor.com/share-35A5_51FFA496.html&quot; rel=&quot;nofollow&quot; target=&quot;_NEW&quot;&gt;\nhttp://www.pixsor.com/share-35A5_51FFA496.html&lt;/a&gt;\n\nDani Daniels - Dani's Hidden Talents\nReleased: August 5, 2013\n\nDani Daniels is working on the deal of a lifetime. An elegant art dealer thinks her paintings are hot commodities, but he's got his eye on another perfect piece of art... Dani's sweet ass. But if he wants this little artist to backdoor her husband, it's not going to come cheap. He flashes the kind of big dollars that make this little honey bend over a work table to take every inch of his fat cock.\n\nFile size                                : 279 MiB\nDuration                                 : 32mn 59s\nWidth                                    : 854 pixels\nHeight                                   : 480 pixels\nDisplay aspect ratio                     : 16:9","torrent":{"xt":"urn:btih:5406625499d786f80ea5d3347a18bc4e6bed2540","amp;dn":"RealWifeStories+-+Dani+Daniels+%2808.05.2013.%29","amp;tr":["udp%3A%2F%2Ftracker.openbittorrent.com%3A80","udp%3A%2F%2Fopen.demonii.com%3A1337","udp%3A%2F%2Ftracker.coppersurfer.tk%3A6969","udp%3A%2F%2Fexodus.desync.com%3A6969"],"infoHash":"5406625499d786f80ea5d3347a18bc4e6bed2540","infoHashBuffer":{"type":"Buffer","data":[84,6,98,84,153,215,134,248,14,165,211,52,122,24,188,78,107,237,37,64]},"announce":[],"urlList":[]}}