{"title":"DPFanatics.13.09.29.Vanda.Lust.XXX.1080p.MP4-KTR","uid":8983839,"size":1472918173,"categoryP":"porn","categoryS":"hd___movies","magnet":"?xt=urn:btih:5b080a247716e6365be28b13201533f9823b2384&amp;dn=DPFanatics.13.09.29.Vanda.Lust.XXX.1080p.MP4-KTR&amp;tr=udp%3A%2F%2Ftracker.openbittorrent.com%3A80&amp;tr=udp%3A%2F%2Fopen.demonii.com%3A1337&amp;tr=udp%3A%2F%2Ftracker.coppersurfer.tk%3A6969&amp;tr=udp%3A%2F%2Fexodus.desync.com%3A6969","seeders":0,"leechers":1,"uploader":"xxxlavalxxx","files":3,"time":1380624507,"description":"DPFanatics.13.09.29.Vanda.Lust.XXX.1080p.MP4-KTR\nGenre.......: Adult\nFiles.......: 1\nVideo.......: MP4\nDate........: 2013-10-01\n\n &lt;a href=&quot;\nhttp://imgdone.com/viewer.php?file=89293667458495082582.jpg&quot; rel=&quot;nofollow&quot; target=&quot;_NEW&quot;&gt;\nhttp://imgdone.com/viewer.php?file=89293667458495082582.jpg&lt;/a&gt;\n &lt;a href=&quot;\nhttp://imgdone.com/viewer.php?file=08015094163500022521.jpg&quot; rel=&quot;nofollow&quot; target=&quot;_NEW&quot;&gt;\nhttp://imgdone.com/viewer.php?file=08015094163500022521.jpg&lt;/a&gt;","torrent":{"xt":"urn:btih:5b080a247716e6365be28b13201533f9823b2384","amp;dn":"DPFanatics.13.09.29.Vanda.Lust.XXX.1080p.MP4-KTR","amp;tr":["udp%3A%2F%2Ftracker.openbittorrent.com%3A80","udp%3A%2F%2Fopen.demonii.com%3A1337","udp%3A%2F%2Ftracker.coppersurfer.tk%3A6969","udp%3A%2F%2Fexodus.desync.com%3A6969"],"infoHash":"5b080a247716e6365be28b13201533f9823b2384","infoHashBuffer":{"type":"Buffer","data":[91,8,10,36,119,22,230,54,91,226,139,19,32,21,51,249,130,59,35,132]},"announce":[],"urlList":[]}}