{"title":"Hachiko - A Dog's Story (2009) PAL","uid":8955917,"size":4632838144,"categoryP":"video","categoryS":"movies_dvdr","magnet":"?xt=urn:btih:5dce60d0e837517a3d7e11387d6e9bb03238bd91&amp;dn=Hachiko+-+A+Dog%27s+Story+%282009%29+PAL&amp;tr=udp%3A%2F%2Ftracker.openbittorrent.com%3A80&amp;tr=udp%3A%2F%2Fopen.demonii.com%3A1337&amp;tr=udp%3A%2F%2Ftracker.coppersurfer.tk%3A6969&amp;tr=udp%3A%2F%2Fexodus.desync.com%3A6969","seeders":0,"leechers":1,"uploader":"Ubehage","files":-1,"time":1379993693,"description":"Hachiko - A Dog's Story (2009)\n------------------------------\n&quot;A true story of faith, devotion and undying love.&quot;\n\nIMDB: &lt;a href=&quot;\nhttp://www.imdb.com/title/tt1028532/&quot; rel=&quot;nofollow&quot; target=&quot;_NEW&quot;&gt;\nhttp://www.imdb.com/title/tt1028532/&lt;/a&gt;\n\nAudio: English\n\nSubs: Danish, Swedish, Norwegian, Finnish, Icelandic\n\nExtra Materials:\n- none.\n\n\nPlot outline:\nThis heartwarming true story is an American adaptation of a Japanese tale about a loyal dog named Hachiko. This very special friend would accompany his master to the train station every day and return each afternoon to greet him after work. Sadly his master departs one day, passes away and never returns to the station. Hachiko faithfully returns to the same spot at the station the very next day, and every day for the next nine years to wait for his beloved master. During his daily visits, Hachiko touches the lives of many who work near and commute through the town square. He teaches the local people love, compassion and above all unyielding loyalty. Today, a bronze statue of Hachiko sits in his waiting spot outside the Shibuya station in Japan as a permanent reminder of his devotion and love. It's almost like real life story, one who loves dogs can link up with this movie so badly.","torrent":{"xt":"urn:btih:5dce60d0e837517a3d7e11387d6e9bb03238bd91","amp;dn":"Hachiko+-+A+Dog%27s+Story+%282009%29+PAL","amp;tr":["udp%3A%2F%2Ftracker.openbittorrent.com%3A80","udp%3A%2F%2Fopen.demonii.com%3A1337","udp%3A%2F%2Ftracker.coppersurfer.tk%3A6969","udp%3A%2F%2Fexodus.desync.com%3A6969"],"infoHash":"5dce60d0e837517a3d7e11387d6e9bb03238bd91","infoHashBuffer":{"type":"Buffer","data":[93,206,96,208,232,55,81,122,61,126,17,56,125,110,155,176,50,56,189,145]},"announce":[],"urlList":[]}}