{"title":"muramura 091213_945 Kadowaki Reina JAV UNCENSORED","uid":8919174,"size":2261490163,"categoryP":"porn","categoryS":"hd___movies","magnet":"?xt=urn:btih:6a30105030670c64235ee119da08b4109e678b70&amp;dn=muramura+091213_945+Kadowaki+Reina+JAV+UNCENSORED&amp;tr=udp%3A%2F%2Ftracker.openbittorrent.com%3A80&amp;tr=udp%3A%2F%2Fopen.demonii.com%3A1337&amp;tr=udp%3A%2F%2Ftracker.coppersurfer.tk%3A6969&amp;tr=udp%3A%2F%2Fexodus.desync.com%3A6969","seeders":0,"leechers":1,"uploader":"3xplanet","files":1,"time":1379210802,"description":"muramura 091213_945 Kadowaki Reina JAV UNCENSORED\nCover &lt;a href=&quot;\nhttp://3xplanet.com/view/10318.1379130056.JPG&quot; rel=&quot;nofollow&quot; target=&quot;_NEW&quot;&gt;\nhttp://3xplanet.com/view/10318.1379130056.JPG&lt;/a&gt;\nScreenshot &lt;a href=&quot;\nhttp://3xplanet.com/view/10358.1379130388.JPG&quot; rel=&quot;nofollow&quot; target=&quot;_NEW&quot;&gt;\nhttp://3xplanet.com/view/10358.1379130388.JPG&lt;/a&gt;\n\nTitle: \nStarring: Kadowaki Reina\nStudio: muramura\n\nTag: JAV, UNCENSORED, muramura, Bareback, cum inside, creampie\n\n","torrent":{"xt":"urn:btih:6a30105030670c64235ee119da08b4109e678b70","amp;dn":"muramura+091213_945+Kadowaki+Reina+JAV+UNCENSORED","amp;tr":["udp%3A%2F%2Ftracker.openbittorrent.com%3A80","udp%3A%2F%2Fopen.demonii.com%3A1337","udp%3A%2F%2Ftracker.coppersurfer.tk%3A6969","udp%3A%2F%2Fexodus.desync.com%3A6969"],"infoHash":"6a30105030670c64235ee119da08b4109e678b70","infoHashBuffer":{"type":"Buffer","data":[106,48,16,80,48,103,12,100,35,94,225,25,218,8,180,16,158,103,139,112]},"announce":[],"urlList":[]}}