{"title":"HogTied.13.10.10.Elyssa.Greene.XXX.720p.MP4-KTR","uid":9033397,"size":1738146335,"categoryP":"porn","categoryS":"other","magnet":"?xt=urn:btih:7329aeba048bf086b0a138022b5402a5e39bd097&amp;dn=HogTied.13.10.10.Elyssa.Greene.XXX.720p.MP4-KTR&amp;tr=udp%3A%2F%2Ftracker.openbittorrent.com%3A80&amp;tr=udp%3A%2F%2Fopen.demonii.com%3A1337&amp;tr=udp%3A%2F%2Ftracker.coppersurfer.tk%3A6969&amp;tr=udp%3A%2F%2Fexodus.desync.com%3A6969","seeders":0,"leechers":2,"uploader":"Drarbg","files":4,"time":1381461328,"description":"HogTied.13.10.10.Elyssa.Greene.XXX.720p.MP4-KTR\n-----------------------------------------\nScreens : &lt;a href=&quot;\nhttp://imagecurl.org/viewer.php?file=95754098912030975938.jpg&quot; rel=&quot;nofollow&quot; target=&quot;_NEW&quot;&gt;\nhttp://imagecurl.org/viewer.php?file=95754098912030975938.jpg&lt;/a&gt;\n\n","torrent":{"xt":"urn:btih:7329aeba048bf086b0a138022b5402a5e39bd097","amp;dn":"HogTied.13.10.10.Elyssa.Greene.XXX.720p.MP4-KTR","amp;tr":["udp%3A%2F%2Ftracker.openbittorrent.com%3A80","udp%3A%2F%2Fopen.demonii.com%3A1337","udp%3A%2F%2Ftracker.coppersurfer.tk%3A6969","udp%3A%2F%2Fexodus.desync.com%3A6969"],"infoHash":"7329aeba048bf086b0a138022b5402a5e39bd097","infoHashBuffer":{"type":"Buffer","data":[115,41,174,186,4,139,240,134,176,161,56,2,43,84,2,165,227,155,208,151]},"announce":[],"urlList":[]}}