{"title":"Backdoor.to.London.XXX.DVDRip.x264-CHiKANi","uid":8935337,"size":1552554378,"categoryP":"porn","categoryS":"other","magnet":"?xt=urn:btih:7693ea4f491ba7f0597cc8c9750778a983301394&amp;dn=Backdoor.to.London.XXX.DVDRip.x264-CHiKANi&amp;tr=udp%3A%2F%2Ftracker.openbittorrent.com%3A80&amp;tr=udp%3A%2F%2Fopen.demonii.com%3A1337&amp;tr=udp%3A%2F%2Ftracker.coppersurfer.tk%3A6969&amp;tr=udp%3A%2F%2Fexodus.desync.com%3A6969","seeders":0,"leechers":1,"uploader":"Pronsta","files":2,"time":1379549975,"description":"\nScreenshots:\n &lt;a href=&quot;\nhttp://magnetxxx.com/showthread.php?52781-Backdoor-to-London-XXX-DVDRip-x264-CHiKANi&quot; rel=&quot;nofollow&quot; target=&quot;_NEW&quot;&gt;\nhttp://magnetxxx.com/showthread.php?52781-Backdoor-to-London-XXX-DVDRip-x264-CHiKANi&lt;/a&gt;\n\n\n\n.","torrent":{"xt":"urn:btih:7693ea4f491ba7f0597cc8c9750778a983301394","amp;dn":"Backdoor.to.London.XXX.DVDRip.x264-CHiKANi","amp;tr":["udp%3A%2F%2Ftracker.openbittorrent.com%3A80","udp%3A%2F%2Fopen.demonii.com%3A1337","udp%3A%2F%2Ftracker.coppersurfer.tk%3A6969","udp%3A%2F%2Fexodus.desync.com%3A6969"],"infoHash":"7693ea4f491ba7f0597cc8c9750778a983301394","infoHashBuffer":{"type":"Buffer","data":[118,147,234,79,73,27,167,240,89,124,200,201,117,7,120,169,131,48,19,148]},"announce":[],"urlList":[]}}