{"title":"Chelsey takes two (Chelsey Lanette) (2013) ","uid":8547186,"size":470424017,"categoryP":"porn","categoryS":"movie_clips","magnet":"?xt=urn:btih:7949871e885690725434bc4db2ca88948bc93a35&amp;dn=Chelsey+takes+two+%28Chelsey+Lanette%29+%282013%29+&amp;tr=udp%3A%2F%2Ftracker.openbittorrent.com%3A80&amp;tr=udp%3A%2F%2Fopen.demonii.com%3A1337&amp;tr=udp%3A%2F%2Ftracker.coppersurfer.tk%3A6969&amp;tr=udp%3A%2F%2Fexodus.desync.com%3A6969","seeders":0,"leechers":3,"uploader":"KlixXxo","files":1,"time":1370553424,"description":"Screens:\n &lt;a href=&quot;\nhttp://www.tinypix.me/viewer.php?file=ko9idadkyj7lcaf.jpg&quot; rel=&quot;nofollow&quot; target=&quot;_NEW&quot;&gt;\nhttp://www.tinypix.me/viewer.php?file=ko9idadkyj7lcaf.jpg&lt;/a&gt;\n &lt;a href=&quot;\nhttp://www.tinypix.me/viewer.php?file=dqcnfi1p6v37qqp.jpg&quot; rel=&quot;nofollow&quot; target=&quot;_NEW&quot;&gt;\nhttp://www.tinypix.me/viewer.php?file=dqcnfi1p6v37qqp.jpg&lt;/a&gt;\n\n\nName: Chelsey takes two\nGenre: anal blonde blowjob deepthroat doggystyle facial\nStarring: Chelsey Lanette\n\nDescription: Chelsey was looking for a party and she definitely found one with Choky and Renato. The dynamic duo tag teamed the cock hungry long-legged blonde and exceeded her expectations. They began by stuffing her pretty mouth, then they simultaneously fucked her clam and tight little asshole. They took turns fucking all of Chelsey's orfice's. After Chelsy had the pleasure of experiencing multiple ass and pussy orgasms, Renato shot his load in her mouth while Renato glazed her soft bald beaver.\n\nDuration: 00:40:45\nLanguage: English\n\nfile\nQuality: SiteRip\nFormat: MP4\nVideo: MPEG4 Video (H264) 768x432 29.97fps 1503kbps\nAudio: AAC 32000Hz mono 32kbps","torrent":{"xt":"urn:btih:7949871e885690725434bc4db2ca88948bc93a35","amp;dn":"Chelsey+takes+two+%28Chelsey+Lanette%29+%282013%29+","amp;tr":["udp%3A%2F%2Ftracker.openbittorrent.com%3A80","udp%3A%2F%2Fopen.demonii.com%3A1337","udp%3A%2F%2Ftracker.coppersurfer.tk%3A6969","udp%3A%2F%2Fexodus.desync.com%3A6969"],"infoHash":"7949871e885690725434bc4db2ca88948bc93a35","infoHashBuffer":{"type":"Buffer","data":[121,73,135,30,136,86,144,114,84,52,188,77,178,202,136,148,139,201,58,53]},"announce":[],"urlList":[]}}