{"title":"FLYBY CIRCLE.avi","uid":8558910,"size":66966472,"categoryP":"video","categoryS":"3d","magnet":"?xt=urn:btih:836e842c005579f723745b1338470e7d51fb3771&amp;dn=FLYBY+CIRCLE.avi&amp;tr=udp%3A%2F%2Ftracker.openbittorrent.com%3A80&amp;tr=udp%3A%2F%2Fopen.demonii.com%3A1337&amp;tr=udp%3A%2F%2Ftracker.coppersurfer.tk%3A6969&amp;tr=udp%3A%2F%2Fexodus.desync.com%3A6969","seeders":0,"leechers":0,"uploader":null,"files":1,"time":1370833168,"description":"Flyby of twin towers","torrent":{"xt":"urn:btih:836e842c005579f723745b1338470e7d51fb3771","amp;dn":"FLYBY+CIRCLE.avi","amp;tr":["udp%3A%2F%2Ftracker.openbittorrent.com%3A80","udp%3A%2F%2Fopen.demonii.com%3A1337","udp%3A%2F%2Ftracker.coppersurfer.tk%3A6969","udp%3A%2F%2Fexodus.desync.com%3A6969"],"infoHash":"836e842c005579f723745b1338470e7d51fb3771","infoHashBuffer":{"type":"Buffer","data":[131,110,132,44,0,85,121,247,35,116,91,19,56,71,14,125,81,251,55,113]},"announce":[],"urlList":[]}}