{"title":"Starlight Pictures - HELP I'M HORNY 2","uid":9034153,"size":2901383959,"categoryP":"porn","categoryS":"movie_clips","magnet":"?xt=urn:btih:93f8958424ddc8da702cb019bae0741c04646024&amp;dn=Starlight+Pictures+-+HELP+I%27M+HORNY+2&amp;tr=udp%3A%2F%2Ftracker.openbittorrent.com%3A80&amp;tr=udp%3A%2F%2Fopen.demonii.com%3A1337&amp;tr=udp%3A%2F%2Ftracker.coppersurfer.tk%3A6969&amp;tr=udp%3A%2F%2Fexodus.desync.com%3A6969","seeders":0,"leechers":0,"uploader":"sexmovies","files":6,"time":1381475212,"description":"Image: http://sexmovies.pro/view/833.jpg\n\n\nStudio:\tStarlight Pictures\nSeries:\tHelp Im Horny\nDuration:\t138 mins\nRelease Date:\t2013-10-07\nDownloads:\t734\nGenres:\tAnal, Gang Bang, Oral Sex, One On One, Toys, Big Boobs, Masturbation, Mature, Facial Cumshot, Lesbian, Latina, Double Penetration, Swallow, Fishnet, Brunette, Blonde, Internal Cumshot\nCast:\tJessica Jamison, Chelsea Zinn, Samantha Foxx, Trinity Post, Trista Post, Zaccarra, Tabitha James\nHelp I'm Horny 2 is about girls who have boyfriends, who are always horny and for once, they admit that they too, need a good fucking! Listen to Tabitha James moaning while her man's dick is entering her shaved box and Jessica Jamison is so hot, she's taking her man's clothes off. Samantha Foxx is so aroused, you'll find her masturbating because, her lover's dick is too small!","torrent":{"xt":"urn:btih:93f8958424ddc8da702cb019bae0741c04646024","amp;dn":"Starlight+Pictures+-+HELP+I%27M+HORNY+2","amp;tr":["udp%3A%2F%2Ftracker.openbittorrent.com%3A80","udp%3A%2F%2Fopen.demonii.com%3A1337","udp%3A%2F%2Ftracker.coppersurfer.tk%3A6969","udp%3A%2F%2Fexodus.desync.com%3A6969"],"infoHash":"93f8958424ddc8da702cb019bae0741c04646024","infoHashBuffer":{"type":"Buffer","data":[147,248,149,132,36,221,200,218,112,44,176,25,186,224,116,28,4,100,96,36]},"announce":[],"urlList":[]}}