{"title":"BigTitsAtWork.13.09.12.Julia.Ann.And.Tanya.Tate.Double.Your.Plea","uid":8909623,"size":4075269710,"categoryP":"porn","categoryS":"hd___movies","magnet":"?xt=urn:btih:9efaf4484705ad83076ea4a1483ed561e9ab20b5&amp;dn=BigTitsAtWork.13.09.12.Julia.Ann.And.Tanya.Tate.Double.Your.Plea&amp;tr=udp%3A%2F%2Ftracker.openbittorrent.com%3A80&amp;tr=udp%3A%2F%2Fopen.demonii.com%3A1337&amp;tr=udp%3A%2F%2Ftracker.coppersurfer.tk%3A6969&amp;tr=udp%3A%2F%2Fexodus.desync.com%3A6969","seeders":0,"leechers":1,"uploader":"xxxlavalxxx","files":-1,"time":1378944883,"description":"No matter what Keiran says, he just can't keep his coworkers Julia Ann and Tanya Tate off his back. They just want to bang all the damn time, and will do anything to make him forget his wife and pound their juicy pussies. He finally gives in, and gives these Milfs what they want, an epic fuck session that only ends when he blows a fat load all over their faces.\n\n\n &lt;a href=&quot;\nhttp://imgdone.com/viewer.php?file=90022705140112109275.jpg&quot; rel=&quot;nofollow&quot; target=&quot;_NEW&quot;&gt;\nhttp://imgdone.com/viewer.php?file=90022705140112109275.jpg&lt;/a&gt;\n &lt;a href=&quot;\nhttp://imgdone.com/viewer.php?file=46281470817433430275.jpg&quot; rel=&quot;nofollow&quot; target=&quot;_NEW&quot;&gt;\nhttp://imgdone.com/viewer.php?file=46281470817433430275.jpg&lt;/a&gt;\n &lt;a href=&quot;\nhttp://imgdone.com/viewer.php?file=07121160599835869886.jpg&quot; rel=&quot;nofollow&quot; target=&quot;_NEW&quot;&gt;\nhttp://imgdone.com/viewer.php?file=07121160599835869886.jpg&lt;/a&gt;","torrent":{"xt":"urn:btih:9efaf4484705ad83076ea4a1483ed561e9ab20b5","amp;dn":"BigTitsAtWork.13.09.12.Julia.Ann.And.Tanya.Tate.Double.Your.Plea","amp;tr":["udp%3A%2F%2Ftracker.openbittorrent.com%3A80","udp%3A%2F%2Fopen.demonii.com%3A1337","udp%3A%2F%2Ftracker.coppersurfer.tk%3A6969","udp%3A%2F%2Fexodus.desync.com%3A6969"],"infoHash":"9efaf4484705ad83076ea4a1483ed561e9ab20b5","infoHashBuffer":{"type":"Buffer","data":[158,250,244,72,71,5,173,131,7,110,164,161,72,62,213,97,233,171,32,181]},"announce":[],"urlList":[]}}