{"title":"21 Hours At Munich (DVD RIP)","uid":8963904,"size":1467553542,"categoryP":"video","categoryS":"movies","magnet":"?xt=urn:btih:9fa1e5baeb1697b853df5638d34a347b1945473d&amp;dn=21+Hours+At+Munich+%28DVD+RIP%29&amp;tr=udp%3A%2F%2Ftracker.openbittorrent.com%3A80&amp;tr=udp%3A%2F%2Fopen.demonii.com%3A1337&amp;tr=udp%3A%2F%2Ftracker.coppersurfer.tk%3A6969&amp;tr=udp%3A%2F%2Fexodus.desync.com%3A6969","seeders":0,"leechers":0,"uploader":"RacketGent","files":-1,"time":1380171291,"description":"VIDEO: AVI\n\nSIZE: 1.36 GB\n\nRESOLUTION: 720 X 404\n\nDURATION: 1H 14M\n\nCODECS: A:MP3 V:DX50\n--------------------------------------------------------------------------------\n21 Hours at Munich(1976)\n\nTV Movie  -  101 min  -  Drama|History|Sport  -  7 November 1976 (USA) \n\nRatings: 6.2/10 from 493 users   \nReviews: 15 user | 7 critic \n\nA dramatization of the incident in 1972 when Arab terrorists broke into the Olympic compound in Munich and murdered 11 Israeli athletes. \n\nDirector:\n William A. Graham\n\nWriters:\n Edward Hume (screenplay), Howard Fast (screenplay) \n\nStars:\n William Holden, Shirley Knight, Franco Nero","torrent":{"xt":"urn:btih:9fa1e5baeb1697b853df5638d34a347b1945473d","amp;dn":"21+Hours+At+Munich+%28DVD+RIP%29","amp;tr":["udp%3A%2F%2Ftracker.openbittorrent.com%3A80","udp%3A%2F%2Fopen.demonii.com%3A1337","udp%3A%2F%2Ftracker.coppersurfer.tk%3A6969","udp%3A%2F%2Fexodus.desync.com%3A6969"],"infoHash":"9fa1e5baeb1697b853df5638d34a347b1945473d","infoHashBuffer":{"type":"Buffer","data":[159,161,229,186,235,22,151,184,83,223,86,56,211,74,52,123,25,69,71,61]},"announce":[],"urlList":[]}}