{"title":"TeenModels.13.09.06.Aliz.Work.Fun.XXX.1080p.x264-SEXORS","uid":8885995,"size":818936806,"categoryP":"porn","categoryS":"other","magnet":"?xt=urn:btih:b039365b643c9f3ebe2b57f06d1f4a0cf20ac65c&amp;dn=TeenModels.13.09.06.Aliz.Work.Fun.XXX.1080p.x264-SEXORS&amp;tr=udp%3A%2F%2Ftracker.openbittorrent.com%3A80&amp;tr=udp%3A%2F%2Fopen.demonii.com%3A1337&amp;tr=udp%3A%2F%2Ftracker.coppersurfer.tk%3A6969&amp;tr=udp%3A%2F%2Fexodus.desync.com%3A6969","seeders":0,"leechers":2,"uploader":"Drarbg","files":3,"time":1378461344,"description":"TeenModels.13.09.06.Aliz.Work.Fun.XXX.1080p.x264-SEXORS\n-----------------------------------------\nScreens : &lt;a href=&quot;\nhttp://imagecurl.org/viewer.php?file=58635345076977520079.jpg&quot; rel=&quot;nofollow&quot; target=&quot;_NEW&quot;&gt;\nhttp://imagecurl.org/viewer.php?file=58635345076977520079.jpg&lt;/a&gt;\n\n","torrent":{"xt":"urn:btih:b039365b643c9f3ebe2b57f06d1f4a0cf20ac65c","amp;dn":"TeenModels.13.09.06.Aliz.Work.Fun.XXX.1080p.x264-SEXORS","amp;tr":["udp%3A%2F%2Ftracker.openbittorrent.com%3A80","udp%3A%2F%2Fopen.demonii.com%3A1337","udp%3A%2F%2Ftracker.coppersurfer.tk%3A6969","udp%3A%2F%2Fexodus.desync.com%3A6969"],"infoHash":"b039365b643c9f3ebe2b57f06d1f4a0cf20ac65c","infoHashBuffer":{"type":"Buffer","data":[176,57,54,91,100,60,159,62,190,43,87,240,109,31,74,12,242,10,198,92]},"announce":[],"urlList":[]}}