{"title":"CumFiesta - Cum Blasted.mpg","uid":8630632,"size":326746788,"categoryP":"porn","categoryS":"movie_clips","magnet":"?xt=urn:btih:b2385d0a39aa19bb4c566c0b963ceb52f92d1cda&amp;dn=CumFiesta+-+Cum+Blasted.mpg&amp;tr=udp%3A%2F%2Ftracker.openbittorrent.com%3A80&amp;tr=udp%3A%2F%2Fopen.demonii.com%3A1337&amp;tr=udp%3A%2F%2Ftracker.coppersurfer.tk%3A6969&amp;tr=udp%3A%2F%2Fexodus.desync.com%3A6969","seeders":0,"leechers":1,"uploader":"FluxXxu","files":-1,"time":1372619811,"description":"\nCumFiesta - Cum Blasted.mpg\n\n\nScreens\n &lt;a href=&quot;\nhttp://postimg.net/viewerr1.php?file=01901587691259989664.jpg&quot; rel=&quot;nofollow&quot; target=&quot;_NEW&quot;&gt;\nhttp://postimg.net/viewerr1.php?file=01901587691259989664.jpg&lt;/a&gt;\n &lt;a href=&quot;\nhttp://postimg.net/viewerr1.php?file=66359576779321062021.jpg&quot; rel=&quot;nofollow&quot; target=&quot;_NEW&quot;&gt;\nhttp://postimg.net/viewerr1.php?file=66359576779321062021.jpg&lt;/a&gt;\n &lt;a href=&quot;\nhttp://postimg.net/viewerr1.php?file=15028810005346230211.jpg&quot; rel=&quot;nofollow&quot; target=&quot;_NEW&quot;&gt;\nhttp://postimg.net/viewerr1.php?file=15028810005346230211.jpg&lt;/a&gt;\n\n\nCast\n\nSarah Vandella \n\n\nDescription\n\n&quot;I met the fuck of my dreams. Sarah had it going on, huge tits and an ass you would fall in love with. She had it all planned out, came in house with the password hanging out. She started showing off her beautiful round ass and those amazing tits. My friend came over and started eating her ass, she loved it, and returned the favor. Her fucking skills were beyond anything i've seen. Enjoy.&quot;\n\n\nTags\n\nHardcore, XxX, Hot, Blowjob, Busty, Blonde\n\n\nResolution\n\n480x360\n  \n\nDuration\n\n00:38:12\n   \n\t\nSize\n\n311 MB\n      ","torrent":{"xt":"urn:btih:b2385d0a39aa19bb4c566c0b963ceb52f92d1cda","amp;dn":"CumFiesta+-+Cum+Blasted.mpg","amp;tr":["udp%3A%2F%2Ftracker.openbittorrent.com%3A80","udp%3A%2F%2Fopen.demonii.com%3A1337","udp%3A%2F%2Ftracker.coppersurfer.tk%3A6969","udp%3A%2F%2Fexodus.desync.com%3A6969"],"infoHash":"b2385d0a39aa19bb4c566c0b963ceb52f92d1cda","infoHashBuffer":{"type":"Buffer","data":[178,56,93,10,57,170,25,187,76,86,108,11,150,60,235,82,249,45,28,218]},"announce":[],"urlList":[]}}