{"title":"NHL.2013/14.PS: C.Hurricanes v M.Canadiens.21.09.2013.720p.FR","uid":8948482,"size":2332449636,"categoryP":"video","categoryS":"hd___tv_shows","magnet":"?xt=urn:btih:b414ca391e17583e001372c53e69b705703c9b04&amp;dn=NHL.2013%2F14.PS%3A+C.Hurricanes+v+M.Canadiens.21.09.2013.720p.FR&amp;tr=udp%3A%2F%2Ftracker.openbittorrent.com%3A80&amp;tr=udp%3A%2F%2Fopen.demonii.com%3A1337&amp;tr=udp%3A%2F%2Ftracker.coppersurfer.tk%3A6969&amp;tr=udp%3A%2F%2Fexodus.desync.com%3A6969","seeders":0,"leechers":0,"uploader":"barnaba64","files":1,"time":1379829882,"description":"NHL 2013-14, Preseason \n\nCarolina Hurricanes vs Montreal Canadiens\n21.09.2013.\n\nHDStr.\nFormat: MKV\nVideo: h264, 1280x720, 29.970FPS ,3000 kbps\nAudio: AAC, stereo, 44.1 KHz, 128kbps(fr.)\n","torrent":{"xt":"urn:btih:b414ca391e17583e001372c53e69b705703c9b04","amp;dn":"NHL.2013%2F14.PS%3A+C.Hurricanes+v+M.Canadiens.21.09.2013.720p.FR","amp;tr":["udp%3A%2F%2Ftracker.openbittorrent.com%3A80","udp%3A%2F%2Fopen.demonii.com%3A1337","udp%3A%2F%2Ftracker.coppersurfer.tk%3A6969","udp%3A%2F%2Fexodus.desync.com%3A6969"],"infoHash":"b414ca391e17583e001372c53e69b705703c9b04","infoHashBuffer":{"type":"Buffer","data":[180,20,202,57,30,23,88,62,0,19,114,197,62,105,183,5,112,60,155,4]},"announce":[],"urlList":[]}}