{"title":"Shane Disel Is In My Ass!_Angel Long_XXX_DVDRip","uid":8988079,"size":1516881920,"categoryP":"porn","categoryS":"movies","magnet":"?xt=urn:btih:be21b219e347adb1fda481671b05be8083b034f3&amp;dn=Shane+Disel+Is+In+My+Ass%21_Angel+Long_XXX_DVDRip&amp;tr=udp%3A%2F%2Ftracker.openbittorrent.com%3A80&amp;tr=udp%3A%2F%2Fopen.demonii.com%3A1337&amp;tr=udp%3A%2F%2Ftracker.coppersurfer.tk%3A6969&amp;tr=udp%3A%2F%2Fexodus.desync.com%3A6969","seeders":0,"leechers":3,"uploader":"m21wolf","files":5,"time":1380724222,"description":"Shane Disel Is In My Ass!_Angel Long_XXX_DVDRip\n\nSize: 1.41 GB\n\nResolution: 640X352\n\nDuration: 1-26m, 2-25m, 3-25m, 4-26m, 5-19m\n\nCover:\n &lt;a href=&quot;\nhttp://www.flickimg.com/KEX&quot; rel=&quot;nofollow&quot; target=&quot;_NEW&quot;&gt;\nhttp://www.flickimg.com/KEX&lt;/a&gt;\n\nThumbnail Screenshot:\n &lt;a href=&quot;\nhttp://www.flickimg.com/KhC&quot; rel=&quot;nofollow&quot; target=&quot;_NEW&quot;&gt;\nhttp://www.flickimg.com/KhC&lt;/a&gt;\n &lt;a href=&quot;\nhttp://www.flickimg.com/KhK&quot; rel=&quot;nofollow&quot; target=&quot;_NEW&quot;&gt;\nhttp://www.flickimg.com/KhK&lt;/a&gt;\n &lt;a href=&quot;\nhttp://www.flickimg.com/KhT&quot; rel=&quot;nofollow&quot; target=&quot;_NEW&quot;&gt;\nhttp://www.flickimg.com/KhT&lt;/a&gt;\n &lt;a href=&quot;\nhttp://www.flickimg.com/Kha&quot; rel=&quot;nofollow&quot; target=&quot;_NEW&quot;&gt;\nhttp://www.flickimg.com/Kha&lt;/a&gt;\n &lt;a href=&quot;\nhttp://www.flickimg.com/Khp&quot; rel=&quot;nofollow&quot; target=&quot;_NEW&quot;&gt;\nhttp://www.flickimg.com/Khp&lt;/a&gt;\n\nDownload, Seed &amp; Enjoy :)","torrent":{"xt":"urn:btih:be21b219e347adb1fda481671b05be8083b034f3","amp;dn":"Shane+Disel+Is+In+My+Ass%21_Angel+Long_XXX_DVDRip","amp;tr":["udp%3A%2F%2Ftracker.openbittorrent.com%3A80","udp%3A%2F%2Fopen.demonii.com%3A1337","udp%3A%2F%2Ftracker.coppersurfer.tk%3A6969","udp%3A%2F%2Fexodus.desync.com%3A6969"],"infoHash":"be21b219e347adb1fda481671b05be8083b034f3","infoHashBuffer":{"type":"Buffer","data":[190,33,178,25,227,71,173,177,253,164,129,103,27,5,190,128,131,176,52,243]},"announce":[],"urlList":[]}}