{"title":"Mothers Forbidden.DVDRip.XxX.mp4","uid":8964236,"size":1284586614,"categoryP":"porn","categoryS":"movies","magnet":"?xt=urn:btih:c06cce7373e0a72c8a4cca4ea0fcef8d7a4e7c6e&amp;dn=Mothers+Forbidden.DVDRip.XxX.mp4&amp;tr=udp%3A%2F%2Ftracker.openbittorrent.com%3A80&amp;tr=udp%3A%2F%2Fopen.demonii.com%3A1337&amp;tr=udp%3A%2F%2Ftracker.coppersurfer.tk%3A6969&amp;tr=udp%3A%2F%2Fexodus.desync.com%3A6969","seeders":0,"leechers":0,"uploader":"handsome_hulk1253","files":1,"time":1380178062,"description":"Screenshots\n &lt;a href=&quot;\nhttp://adultxpictures.com/xxx/4mk&quot; rel=&quot;nofollow&quot; target=&quot;_NEW&quot;&gt;\nhttp://adultxpictures.com/xxx/4mk&lt;/a&gt; &lt;a href=&quot;\nhttp://adultxpictures.com/xxx/4mp&quot; rel=&quot;nofollow&quot; target=&quot;_NEW&quot;&gt;\nhttp://adultxpictures.com/xxx/4mp&lt;/a&gt;","torrent":{"xt":"urn:btih:c06cce7373e0a72c8a4cca4ea0fcef8d7a4e7c6e","amp;dn":"Mothers+Forbidden.DVDRip.XxX.mp4","amp;tr":["udp%3A%2F%2Ftracker.openbittorrent.com%3A80","udp%3A%2F%2Fopen.demonii.com%3A1337","udp%3A%2F%2Ftracker.coppersurfer.tk%3A6969","udp%3A%2F%2Fexodus.desync.com%3A6969"],"infoHash":"c06cce7373e0a72c8a4cca4ea0fcef8d7a4e7c6e","infoHashBuffer":{"type":"Buffer","data":[192,108,206,115,115,224,167,44,138,76,202,78,160,252,239,141,122,78,124,110]},"announce":[],"urlList":[]}}