{"title":"Mirabella - Unconditional Love HD 1080p","uid":8945416,"size":761569970,"categoryP":"porn","categoryS":"hd___movies","magnet":"?xt=urn:btih:cbb7aed0d15dca50a176c11381ed7ea19588dcd0&amp;dn=Mirabella+-+Unconditional+Love+HD+1080p&amp;tr=udp%3A%2F%2Ftracker.openbittorrent.com%3A80&amp;tr=udp%3A%2F%2Fopen.demonii.com%3A1337&amp;tr=udp%3A%2F%2Ftracker.coppersurfer.tk%3A6969&amp;tr=udp%3A%2F%2Fexodus.desync.com%3A6969","seeders":0,"leechers":1,"uploader":"ElitePorn","files":-1,"time":1379762463,"description":"Mirabella - Unconditional Love HD 1080p\n---------------------------------------\n\nScreenshots:\n------------\n &lt;a href=&quot;\nhttp://imagescream.com/img/soft/AiJ&quot; rel=&quot;nofollow&quot; target=&quot;_NEW&quot;&gt;\nhttp://imagescream.com/img/soft/AiJ&lt;/a&gt;\n &lt;a href=&quot;\nhttp://imagescream.com/img/soft/AiW&quot; rel=&quot;nofollow&quot; target=&quot;_NEW&quot;&gt;\nhttp://imagescream.com/img/soft/AiW&lt;/a&gt;\n &lt;a href=&quot;\nhttp://imagescream.com/img/soft/Aih&quot; rel=&quot;nofollow&quot; target=&quot;_NEW&quot;&gt;\nhttp://imagescream.com/img/soft/Aih&lt;/a&gt;\n &lt;a href=&quot;\nhttp://imagescream.com/img/soft/Ai3&quot; rel=&quot;nofollow&quot; target=&quot;_NEW&quot;&gt;\nhttp://imagescream.com/img/soft/Ai3&lt;/a&gt;\n\n\nDuration: 22:05, Format: MP4, Resolution: 1920x1080, Size: 726.29 MB","torrent":{"xt":"urn:btih:cbb7aed0d15dca50a176c11381ed7ea19588dcd0","amp;dn":"Mirabella+-+Unconditional+Love+HD+1080p","amp;tr":["udp%3A%2F%2Ftracker.openbittorrent.com%3A80","udp%3A%2F%2Fopen.demonii.com%3A1337","udp%3A%2F%2Ftracker.coppersurfer.tk%3A6969","udp%3A%2F%2Fexodus.desync.com%3A6969"],"infoHash":"cbb7aed0d15dca50a176c11381ed7ea19588dcd0","infoHashBuffer":{"type":"Buffer","data":[203,183,174,208,209,93,202,80,161,118,193,19,129,237,126,161,149,136,220,208]},"announce":[],"urlList":[]}}