{"title":"Amateur Hardcore 15","uid":9027381,"size":991748503,"categoryP":"porn","categoryS":"movies","magnet":"?xt=urn:btih:d0a6a62c37f3f506fe87921762a4430dab6528a7&amp;dn=Amateur+Hardcore+15&amp;tr=udp%3A%2F%2Ftracker.openbittorrent.com%3A80&amp;tr=udp%3A%2F%2Fopen.demonii.com%3A1337&amp;tr=udp%3A%2F%2Ftracker.coppersurfer.tk%3A6969&amp;tr=udp%3A%2F%2Fexodus.desync.com%3A6969","seeders":0,"leechers":3,"uploader":"digital_ripper","files":1,"time":1381386965,"description":"screens\n &lt;a href=&quot;\nhttp://www.mypornimage.com/adultimage/pFN&quot; rel=&quot;nofollow&quot; target=&quot;_NEW&quot;&gt;\nhttp://www.mypornimage.com/adultimage/pFN&lt;/a&gt; &lt;a href=&quot;\nhttp://www.mypornimage.com/adultimage/pFP&quot; rel=&quot;nofollow&quot; target=&quot;_NEW&quot;&gt;\nhttp://www.mypornimage.com/adultimage/pFP&lt;/a&gt;\n\n\n~~~~~~~~~~~~~~~~~~~~~~~~~~~~~~~~~~~~~~~~~~~~~~~~~~~~~~~~~~~~~~~~~~~~~~~~~~~~~~~\n\n                       ````````````````````````````````\n                   Watch this porn videos at sexseevideo\n~~~~~~~~~~~~~~~~~~~~~~~~~~~~~~~~~~~~~~~~~~~~~~~~~~~~~~~~~~~~~~~~~~~~~~~~~~~~~~~","torrent":{"xt":"urn:btih:d0a6a62c37f3f506fe87921762a4430dab6528a7","amp;dn":"Amateur+Hardcore+15","amp;tr":["udp%3A%2F%2Ftracker.openbittorrent.com%3A80","udp%3A%2F%2Fopen.demonii.com%3A1337","udp%3A%2F%2Ftracker.coppersurfer.tk%3A6969","udp%3A%2F%2Fexodus.desync.com%3A6969"],"infoHash":"d0a6a62c37f3f506fe87921762a4430dab6528a7","infoHashBuffer":{"type":"Buffer","data":[208,166,166,44,55,243,245,6,254,135,146,23,98,164,67,13,171,101,40,167]},"announce":[],"urlList":[]}}