{"title":"IPZ-199 Sayuri Honjo JAV CENSORED","uid":8924462,"size":1658354685,"categoryP":"porn","categoryS":"movie_clips","magnet":"?xt=urn:btih:d95c69b53e27b2f42d089244b78c05aea84d6a5c&amp;dn=IPZ-199+Sayuri+Honjo+JAV+CENSORED&amp;tr=udp%3A%2F%2Ftracker.openbittorrent.com%3A80&amp;tr=udp%3A%2F%2Fopen.demonii.com%3A1337&amp;tr=udp%3A%2F%2Ftracker.coppersurfer.tk%3A6969&amp;tr=udp%3A%2F%2Fexodus.desync.com%3A6969","seeders":0,"leechers":1,"uploader":"3xplanet","files":1,"time":1379289843,"description":"IPZ-199 Sayuri Honjo JAV CENSORED\nCover &lt;a href=&quot;\nhttp://3xplanet.com/view/10543.1379295856.JPG&quot; rel=&quot;nofollow&quot; target=&quot;_NEW&quot;&gt;\nhttp://3xplanet.com/view/10543.1379295856.JPG&lt;/a&gt;\nScreenshot &lt;a href=&quot;\nhttp://3xplanet.com/view/10589.1379296217.JPG&quot; rel=&quot;nofollow&quot; target=&quot;_NEW&quot;&gt;\nhttp://3xplanet.com/view/10589.1379296217.JPG&lt;/a&gt;\n\nTitle: legendary beauty revival\nStarring: Sayuri Honjo\nStudio: Idea Pocket\n\nTag: JAV, CENSORED, Idea Pocket, Slender, Work Alone\n\n","torrent":{"xt":"urn:btih:d95c69b53e27b2f42d089244b78c05aea84d6a5c","amp;dn":"IPZ-199+Sayuri+Honjo+JAV+CENSORED","amp;tr":["udp%3A%2F%2Ftracker.openbittorrent.com%3A80","udp%3A%2F%2Fopen.demonii.com%3A1337","udp%3A%2F%2Ftracker.coppersurfer.tk%3A6969","udp%3A%2F%2Fexodus.desync.com%3A6969"],"infoHash":"d95c69b53e27b2f42d089244b78c05aea84d6a5c","infoHashBuffer":{"type":"Buffer","data":[217,92,105,181,62,39,178,244,45,8,146,68,183,140,5,174,168,77,106,92]},"announce":[],"urlList":[]}}