{"title":"The Final Drive_720p.HDTV.x264_8-31-2013_TTL","uid":8872366,"size":1322975493,"categoryP":"video","categoryS":"hd___tv_shows","magnet":"?xt=urn:btih:e42eb6d8541bfbc004922c83197017353ee236bb&amp;dn=The+Final+Drive_720p.HDTV.x264_8-31-2013_TTL&amp;tr=udp%3A%2F%2Ftracker.openbittorrent.com%3A80&amp;tr=udp%3A%2F%2Fopen.demonii.com%3A1337&amp;tr=udp%3A%2F%2Ftracker.coppersurfer.tk%3A6969&amp;tr=udp%3A%2F%2Fexodus.desync.com%3A6969","seeders":0,"leechers":1,"uploader":"thetorrentlord","files":-1,"time":1378096555,"description":"This is from the BTN and is a recap of all the games from Fri. and Sat.\t\t\t\t\n\n\t\t\t\t\t\t\t\t\t\t\t\t\n\n\t\t\t\t\t\t\t\t\t\t\t\t\n\n\t\t\t\t\t\t\t\t\t\t\t\t\n\nEnjoy and please share.\t\t\t\t\t\t\t\t\t\t\n\n\t\t\t\t\t\t\t\t\t\t\t\t\n\n\t\t\t\t\t\t\t\t\t\t\t\n\nTTLTTLTTLTTLTTLTTLTTLTTLTTLTTLTTLTTLTTLTTLTTLTTLTTLTTLTTLTTL\t\t\t\t\t\n\n\t\t\t\t\t\t\t\t\t\t\t\t\n\n\t\t\t\t\t\t\t\t\t\t\t\t\n\nThe Final Drive_720p.HDTV.x264_8-31-2013_TTL.mkv\nFormat                           : Matroska\nFile size                        : 1.20 GiB\nDuration                         : 43mn 33s\nOverall bit rate                 : 3 932 Kbps\nWriting application              : HandBrake 0.9.5\nWriting library                  : libmkv 0.6.4.1\n\nVideo\nID                               : 1\nFormat                           : AVC\nFormat/Info                      : Advanced Video Codec\nFormat profile                   : &lt;a class=&quot;__cf_email__&quot; href=&quot;/cdn-cgi/l/email-protection&quot; data-cfemail=&quot;e6ae8f818ea6aad5c8d7&quot;&gt;[email&amp;#160;protected]&lt;/a&gt;&lt;script cf-hash='f9e31' type=&quot;text/javascript&quot;&gt;\n/* &lt;![CDATA[ */!function(){try{var t=&quot;currentScript&quot;in document?document.currentScript:function(){for(var t=document.getElementsByTagName(&quot;script&quot;),e=t.length;e--;)if(t[e].getAttribute(&quot;cf-hash&quot;))return t[e]}();if(t&amp;&amp;t.previousSibling){var e,r,n,i,c=t.previousSibling,a=c.getAttribute(&quot;data-cfemail&quot;);if(a){for(e=&quot;&quot;,r=parseInt(a.substr(0,2),16),n=2;a.length-n;n+=2)i=parseInt(a.substr(n,2),16)^r,e+=String.fromCharCode(i);e=document.createTextNode(e),c.parentNode.replaceChild(e,c)}}}catch(u){}}();/* ]]&gt; */&lt;/script&gt;\nFormat settings, CABAC           : Yes\nFormat settings, ReFrames        : 4 frames\nMuxing mode                      : Container profile=&lt;a class=&quot;__cf_email__&quot; href=&quot;/cdn-cgi/l/email-protection&quot; data-cfemail=&quot;3b6e555055544c557b08150a&quot;&gt;[email&amp;#160;protected]&lt;/a&gt;&lt;script cf-hash='f9e31' type=&quot;text/javascript&quot;&gt;\n/* &lt;![CDATA[ */!function(){try{var t=&quot;currentScript&quot;in document?document.currentScript:function(){for(var t=document.getElementsByTagName(&quot;script&quot;),e=t.length;e--;)if(t[e].getAttribute(&quot;cf-hash&quot;))return t[e]}();if(t&amp;&amp;t.previousSibling){var e,r,n,i,c=t.previousSibling,a=c.getAttribute(&quot;data-cfemail&quot;);if(a){for(e=&quot;&quot;,r=parseInt(a.substr(0,2),16),n=2;a.length-n;n+=2)i=parseInt(a.substr(n,2),16)^r,e+=String.fromCharCode(i);e=document.createTextNode(e),c.parentNode.replaceChild(e,c)}}}catch(u){}}();/* ]]&gt; */&lt;/script&gt;\nCodec ID                         : V_MPEG4/ISO/AVC\nDuration                         : 43mn 33s\nNominal bit rate                 : 3 767 Kbps\nWidth                            : 1 280 pixels\nHeight                           : 720 pixels\nDisplay aspect ratio             : 16:9\nFrame rate mode                  : Variable\nFrame rate                       : 29.970 fps\nColor space                      : YUV\nChroma subsampling               : 4:2:0\nBit depth                        : 8 bits\nScan type                        : Progressive\nBits/(Pixel*Frame)               : 0.136\nWriting library                  : x264 core 112\n\nAudio\nID                               : 2\nFormat                           : AAC\nFormat/Info                      : Advanced Audio Codec\nFormat version                   : Version 4\nFormat profile                   : LC\nFormat settings, SBR             : No\nCodec ID                         : A_AAC\nDuration                         : 43mn 33s\nChannel(s)                       : 2 channels\nChannel positions                : Front: L R\nSampling rate                    : 48.0 KHz\n\n\n","torrent":{"xt":"urn:btih:e42eb6d8541bfbc004922c83197017353ee236bb","amp;dn":"The+Final+Drive_720p.HDTV.x264_8-31-2013_TTL","amp;tr":["udp%3A%2F%2Ftracker.openbittorrent.com%3A80","udp%3A%2F%2Fopen.demonii.com%3A1337","udp%3A%2F%2Ftracker.coppersurfer.tk%3A6969","udp%3A%2F%2Fexodus.desync.com%3A6969"],"infoHash":"e42eb6d8541bfbc004922c83197017353ee236bb","infoHashBuffer":{"type":"Buffer","data":[228,46,182,216,84,27,251,192,4,146,44,131,25,112,23,53,62,226,54,187]},"announce":[],"urlList":[]}}