{"title":"Whose Line Is It Anyway US - Complete Seasons 1-9","uid":8965510,"size":38762778154,"categoryP":"video","categoryS":"tv_shows","magnet":"?xt=urn:btih:f013e4f152f5d581234d98cb0893ac3306dee85b&amp;dn=Whose+Line+Is+It+Anyway+US+-+Complete+Seasons+1-9&amp;tr=udp%3A%2F%2Ftracker.openbittorrent.com%3A80&amp;tr=udp%3A%2F%2Fopen.demonii.com%3A1337&amp;tr=udp%3A%2F%2Ftracker.coppersurfer.tk%3A6969&amp;tr=udp%3A%2F%2Fexodus.desync.com%3A6969","seeders":0,"leechers":15,"uploader":"bindobud","files":271,"time":1380212171,"description":"Whose Line Is It Anyway US - Complete Series 1-9 (231 episodes)\n\nAll 9 seasons of the American TV show Whose Line Is It Anyway? from August 5 1998 to September 24 2013.\n\nEarly seasons are poor quality due to being ripped from VCR recordings, but quality increases as seasons go on, all the way through to season 9, which is mostly HD files of around 500mb each.","torrent":{"xt":"urn:btih:f013e4f152f5d581234d98cb0893ac3306dee85b","amp;dn":"Whose+Line+Is+It+Anyway+US+-+Complete+Seasons+1-9","amp;tr":["udp%3A%2F%2Ftracker.openbittorrent.com%3A80","udp%3A%2F%2Fopen.demonii.com%3A1337","udp%3A%2F%2Ftracker.coppersurfer.tk%3A6969","udp%3A%2F%2Fexodus.desync.com%3A6969"],"infoHash":"f013e4f152f5d581234d98cb0893ac3306dee85b","infoHashBuffer":{"type":"Buffer","data":[240,19,228,241,82,245,213,129,35,77,152,203,8,147,172,51,6,222,232,91]},"announce":[],"urlList":[]}}