{"title":"Rissa Maxx - Maxx Satisfaction HD 1080p","uid":8933120,"size":2398362986,"categoryP":"porn","categoryS":"hd___movies","magnet":"?xt=urn:btih:f74bfbc23e36082f7862a1b2c7d5b47e736fdf3e&amp;dn=Rissa+Maxx+-+Maxx+Satisfaction+HD+1080p&amp;tr=udp%3A%2F%2Ftracker.openbittorrent.com%3A80&amp;tr=udp%3A%2F%2Fopen.demonii.com%3A1337&amp;tr=udp%3A%2F%2Ftracker.coppersurfer.tk%3A6969&amp;tr=udp%3A%2F%2Fexodus.desync.com%3A6969","seeders":0,"leechers":0,"uploader":"ElitePorn","files":-1,"time":1379498394,"description":"Rissa Maxx - Maxx Satisfaction HD 1080p\n---------------------------------------\n\nScreenshots:\n------------\n\n &lt;a href=&quot;\nhttp://imagescream.com/img/soft/tpM&quot; rel=&quot;nofollow&quot; target=&quot;_NEW&quot;&gt;\nhttp://imagescream.com/img/soft/tpM&lt;/a&gt;\n &lt;a href=&quot;\nhttp://imagescream.com/img/soft/tpN&quot; rel=&quot;nofollow&quot; target=&quot;_NEW&quot;&gt;\nhttp://imagescream.com/img/soft/tpN&lt;/a&gt;\n &lt;a href=&quot;\nhttp://imagescream.com/img/soft/tpV&quot; rel=&quot;nofollow&quot; target=&quot;_NEW&quot;&gt;\nhttp://imagescream.com/img/soft/tpV&lt;/a&gt;\n &lt;a href=&quot;\nhttp://imagescream.com/img/soft/tps&quot; rel=&quot;nofollow&quot; target=&quot;_NEW&quot;&gt;\nhttp://imagescream.com/img/soft/tps&lt;/a&gt;\n &lt;a href=&quot;\nhttp://imagescream.com/img/soft/tp9&quot; rel=&quot;nofollow&quot; target=&quot;_NEW&quot;&gt;\nhttp://imagescream.com/img/soft/tp9&lt;/a&gt;\n &lt;a href=&quot;\nhttp://imagescream.com/img/soft/tpX&quot; rel=&quot;nofollow&quot; target=&quot;_NEW&quot;&gt;\nhttp://imagescream.com/img/soft/tpX&lt;/a&gt;\n &lt;a href=&quot;\nhttp://imagescream.com/img/soft/tpd&quot; rel=&quot;nofollow&quot; target=&quot;_NEW&quot;&gt;\nhttp://imagescream.com/img/soft/tpd&lt;/a&gt;\n &lt;a href=&quot;\nhttp://imagescream.com/img/soft/tpf&quot; rel=&quot;nofollow&quot; target=&quot;_NEW&quot;&gt;\nhttp://imagescream.com/img/soft/tpf&lt;/a&gt;\n &lt;a href=&quot;\nhttp://imagescream.com/img/soft/tpy&quot; rel=&quot;nofollow&quot; target=&quot;_NEW&quot;&gt;\nhttp://imagescream.com/img/soft/tpy&lt;/a&gt;\n\n\nDuration: 31:23, Format: MP4, Resolution: 1920x1080, Size: 2.234 GB","torrent":{"xt":"urn:btih:f74bfbc23e36082f7862a1b2c7d5b47e736fdf3e","amp;dn":"Rissa+Maxx+-+Maxx+Satisfaction+HD+1080p","amp;tr":["udp%3A%2F%2Ftracker.openbittorrent.com%3A80","udp%3A%2F%2Fopen.demonii.com%3A1337","udp%3A%2F%2Ftracker.coppersurfer.tk%3A6969","udp%3A%2F%2Fexodus.desync.com%3A6969"],"infoHash":"f74bfbc23e36082f7862a1b2c7d5b47e736fdf3e","infoHashBuffer":{"type":"Buffer","data":[247,75,251,194,62,54,8,47,120,98,161,178,199,213,180,126,115,111,223,62]},"announce":[],"urlList":[]}}