{"title":"wb-df158","uid":8660634,"size":5533958404,"categoryP":"porn","categoryS":"movies","magnet":"?xt=urn:btih:f88cd871a2e8f25d8e7923c346945a9d8a324d16&amp;dn=wb-df158&amp;tr=udp%3A%2F%2Ftracker.openbittorrent.com%3A80&amp;tr=udp%3A%2F%2Fopen.demonii.com%3A1337&amp;tr=udp%3A%2F%2Ftracker.coppersurfer.tk%3A6969&amp;tr=udp%3A%2F%2Fexodus.desync.com%3A6969","seeders":0,"leechers":0,"uploader":"shae2005","files":2,"time":1373312912,"description":"WB-DF158(SD)-Medium\nDouble Feature\nWB-DF158-1\nInfo:\nOne-man anal show Mike Adriano is at it again with \nFive of the prettiest young anal princesses in the \nbusiness stretch their personal boundaries for our \nenjoyment! Mike uses inflatable butt plugs, \nspeculums and his own God-given cock to delve \ndeep into female anal cavities, with POV-style \nsegments that put the viewer in the driver seat. \nLively brunette Chanel Preston tests her recent \ndecision to do on-camera anal sex with a nasty \nreaming that features lots of wet, sloppy \ndicksucking, ass-expanding toys and ass-to-mouth \nnastiness. Chanel gets her bunghole fucked wide \nopen and accepts a creamy oral cum shot.Next \ncomes fresh and lovely Brooke Lee Adams, a \nstunning brunette with a fine, plump ass and \nenticing, all-natural boobs with large nipples. \nThis obedient beauty takes an extra measure of \nanal punishment with an inflatable ass toy and \nan ass-fucking that leaves her poor rear opening \npuffy and gaping. She gamely slurps Mike`s tool \nwith lots of slobber, tonguing his nuts and getting \nan open-mouth facial.Naturally stacked Latina \ncutie Halie James says she`s never had anal \nsex before; she won`t be able to say that now! \nBut will she be able to sit? This pretty senorita \nundergoes a strict course of face-fucking, \nball-licking, girl-on-guy rim-jobbing, tit jobs and \nlots of intense butt-banging. And takes her facial \nwith a smile!Young Jada Stevens has dark hair \nand perfect, little natural tits. Mike eats her asshole \nand inserts his trusty speculum to illuminate her \nmost private zone. Jada accepts his cock in her \ndiminutive ass, then makes rhythmic gagging \nsounds while sucking it straight from her back \ndoor. She impales her butt on his large dick, \ngetting a faceful of sperm for her effort.Sweet, \ntattooed blonde Nichole Taylor has an \nanything-goes attitude. She licks Mike`s taint \nand sucks his raging cock, submits to a speculum \nprobing and is shocked when it opens her \nsphincter to its highest setting! She exudes \nwhitish pussy juice, which Mike uses to lubricate \nhis way up her battered butthole. A vacuum pump \nis employed to swell Nichole`s anal ring to cartoonish dimensions, and when Mike cums into a martini \nglass, she swigs the cocktail in one gulp!\nCast:\nScene 1. Chanel Preston, Mike Adriano \nScene 2. Brooke Lee Adams, Mike Adriano \nScene 3. Halie James, Mike Adriano \nScene 4. Jada Stevens, Mike Adriano \nScene 5. Nichole Taylor, Mike Adriano\nAVI\n3:11:38\n640x352\n3.79gbs\nVideo Specs\nInput Type : XVID(GVC)\nInput Size : 640 x 352\nOutput Type : YUY2\nOutput Size : 640 x 352\nFrameRate(Frame/sec) : 0.00 (29.97)\nAudio Specs\nSampleRate(Sample/sec) : 44100\nBitRate(Bit/sample) : 16\nChannels : 2\nKBitRate(KBit/sec) : 320\nWB-DF158-2\nInfo:\nIn our latest release, we bring you five new and \nsteaming stories of the best Private sex. Also \nincluded for your enjoyment are two extra reports \nfrom the movies Fetish Academy and Calendar Girl.\nCast:\nAllisa, Barbarella, Fabiola, Pocahontas, \nSamanta, Sasha Woman, Stacy Silver, Tina\nMKV\n1:30:17\n720x416\n1.36gbs\nVideo Specs\nInput Type : AVC1(GVC)\nInput Size : 720 x 416\nOutput Type : YUY2\nOutput Size : 720 x 416\nFrameRate(Frame/sec) : 0.00 (29.97)\nAudio Specs\nSampleRate(Sample/sec) : 48000\nBitRate(Bit/sample) : 16\nChannels : 2\nKBitRate(KBit/sec) : 192 Kbps\nPreview &lt;a href=&quot;\nhttp://bayimg.com/KaMcbAaED&quot; rel=&quot;nofollow&quot; target=&quot;_NEW&quot;&gt;\nhttp://bayimg.com/KaMcbAaED&lt;/a&gt;","torrent":{"xt":"urn:btih:f88cd871a2e8f25d8e7923c346945a9d8a324d16","amp;dn":"wb-df158","amp;tr":["udp%3A%2F%2Ftracker.openbittorrent.com%3A80","udp%3A%2F%2Fopen.demonii.com%3A1337","udp%3A%2F%2Ftracker.coppersurfer.tk%3A6969","udp%3A%2F%2Fexodus.desync.com%3A6969"],"infoHash":"f88cd871a2e8f25d8e7923c346945a9d8a324d16","infoHashBuffer":{"type":"Buffer","data":[248,140,216,113,162,232,242,93,142,121,35,195,70,148,90,157,138,50,77,22]},"announce":[],"urlList":[]}}